AUTHORS
CHANGES
LICENSE
MANIFEST.in
Makefile
README
conftest.py
setup.cfg
setup.py
tox.ini
Py3Babel.egg-info/PKG-INFO
Py3Babel.egg-info/SOURCES.txt
Py3Babel.egg-info/dependency_links.txt
Py3Babel.egg-info/entry_points.txt
Py3Babel.egg-info/not-zip-safe
Py3Babel.egg-info/requires.txt
Py3Babel.egg-info/top_level.txt
docs/Makefile
docs/changelog.rst
docs/cmdline.rst
docs/conf.py
docs/dates.rst
docs/index.rst
docs/installation.rst
docs/intro.rst
docs/license.rst
docs/locale.rst
docs/make.bat
docs/messages.rst
docs/numbers.rst
docs/setup.rst
docs/support.rst
docs/_static/logo.pdf
docs/_static/logo.png
docs/_static/logo_small.png
docs/_templates/sidebar-about.html
docs/_templates/sidebar-links.html
docs/_templates/sidebar-logo.html
docs/_themes/LICENSE
docs/_themes/README
docs/_themes/babel/layout.html
docs/_themes/babel/relations.html
docs/_themes/babel/theme.conf
docs/_themes/babel/static/babel.css_t
docs/_themes/babel/static/small_babel.css
docs/api/core.rst
docs/api/dates.rst
docs/api/index.rst
docs/api/numbers.rst
docs/api/plural.rst
docs/api/support.rst
docs/api/messages/catalog.rst
docs/api/messages/extract.rst
docs/api/messages/index.rst
docs/api/messages/mofile.rst
docs/api/messages/pofile.rst
py3babel/__init__.py
py3babel/_compat.py
py3babel/core.py
py3babel/dates.py
py3babel/global.dat
py3babel/localedata.py
py3babel/numbers.py
py3babel/plural.py
py3babel/support.py
py3babel/util.py
py3babel/localedata/aa.dat
py3babel/localedata/aa_DJ.dat
py3babel/localedata/aa_ER.dat
py3babel/localedata/aa_ET.dat
py3babel/localedata/af.dat
py3babel/localedata/af_NA.dat
py3babel/localedata/af_ZA.dat
py3babel/localedata/agq.dat
py3babel/localedata/agq_CM.dat
py3babel/localedata/ak.dat
py3babel/localedata/ak_GH.dat
py3babel/localedata/am.dat
py3babel/localedata/am_ET.dat
py3babel/localedata/ar.dat
py3babel/localedata/ar_001.dat
py3babel/localedata/ar_AE.dat
py3babel/localedata/ar_BH.dat
py3babel/localedata/ar_DJ.dat
py3babel/localedata/ar_DZ.dat
py3babel/localedata/ar_EG.dat
py3babel/localedata/ar_EH.dat
py3babel/localedata/ar_ER.dat
py3babel/localedata/ar_IL.dat
py3babel/localedata/ar_IQ.dat
py3babel/localedata/ar_JO.dat
py3babel/localedata/ar_KM.dat
py3babel/localedata/ar_KW.dat
